django_szuprefix/.DS_Store
django_szuprefix/__init__.py
django_szuprefix/api/__init__.py
django_szuprefix/api/apps.py
django_szuprefix/api/decorators.py
django_szuprefix/api/filters.py
django_szuprefix/api/helper.py
django_szuprefix/api/metadata.py
django_szuprefix/api/mixins.py
django_szuprefix/api/paginations.py
django_szuprefix/api/permissions.py
django_szuprefix/api/signals.py
django_szuprefix/api/urls.py
django_szuprefix/api/views.py
django_szuprefix/auth/__init__.py
django_szuprefix/auth/admins.py
django_szuprefix/auth/apis.py
django_szuprefix/auth/apps.py
django_szuprefix/auth/auth_backends.py
django_szuprefix/auth/authentications.py
django_szuprefix/auth/filters.py
django_szuprefix/auth/helper.py
django_szuprefix/auth/permissions.py
django_szuprefix/auth/receivers.py
django_szuprefix/auth/serializers.py
django_szuprefix/auth/signals.py
django_szuprefix/auth/stats.py
django_szuprefix/auth/urls.py
django_szuprefix/auth/views.py
django_szuprefix/common/__init__.py
django_szuprefix/common/admin.py
django_szuprefix/common/apis.py
django_szuprefix/common/apps.py
django_szuprefix/common/forms.py
django_szuprefix/common/helper.py
django_szuprefix/common/mixins.py
django_szuprefix/common/models.py
django_szuprefix/common/receivers.py
django_szuprefix/common/serializers.py
django_szuprefix/common/signals.py
django_szuprefix/common/tasks.py
django_szuprefix/common/tests.py
django_szuprefix/common/urls.py
django_szuprefix/common/views.py
django_szuprefix/common/migrations/0001_initial.py
django_szuprefix/common/migrations/0002_auto_20180312_1311.py
django_szuprefix/common/migrations/0003_auto_20180323_1134.py
django_szuprefix/common/migrations/0004_trash_object_name.py
django_szuprefix/common/migrations/0005_auto_20180608_1922.py
django_szuprefix/common/migrations/0006_event.py
django_szuprefix/common/migrations/0007_auto_20190416_1622.py
django_szuprefix/common/migrations/0008_auto_20191013_1927.py
django_szuprefix/common/migrations/0009_auto_20200302_1500.py
django_szuprefix-0.11.7.dist-info/METADATA
django_szuprefix-0.11.7.dist-info/WHEEL
django_szuprefix-0.11.7.dist-info/pbr.json
django_szuprefix-0.11.7.dist-info/top_level.txt
django_szuprefix-0.11.7.dist-info/RECORD
