Metadata-Version: 2.1
Name: django-szuprefix
Version: 0.11.7
Summary: my utils in django
Home-page: https://github.com/szuprefix/django_szuprefix
Author: Denis Huang
Author-email: szuprefix@126.com
License: MIT
Platform: UNKNOWN
Classifier: Environment :: Web Environment
Classifier: Intended Audience :: Developers
Classifier: Operating System :: OS Independent
Classifier: Topic :: Text Processing :: Indexing
Classifier: Topic :: Utilities
Classifier: Topic :: Internet
Classifier: Topic :: Software Development :: Libraries :: Python Modules
Classifier: Programming Language :: Python
Classifier: Programming Language :: Python :: 2
Classifier: Programming Language :: Python :: 2.7
Classifier: Programming Language :: Python :: 3
Requires-Dist: django (>=1.11.2)
Requires-Dist: lxml
Requires-Dist: python-dateutil
Requires-Dist: django-tables2
Requires-Dist: django-excel-response
Requires-Dist: xlrd
Requires-Dist: xlwt
Requires-Dist: dwebsocket
